Metadata-Version: 2.1
Name: users-proxy
Version: 8.0
Summary: By @A_T_9 In telegram 
Author: Programmer RESS 
Classifier: Programming Language :: Python :: 3
Classifier: Operating System :: OS Independent
Classifier: License :: OSI Approved :: MIT License
License-File: LICENSE.txt
